setup.py
TiniLang/__init__.py
TiniLang/__main__.py
TiniLang/cli.py
TiniLang/interpreter.py
TiniLang/translator.py
TiniLang-1.0.dist-info/LICENSE
TiniLang-1.0.dist-info/METADATA
TiniLang-1.0.dist-info/WHEEL
TiniLang-1.0.dist-info/entry_points.txt
TiniLang-1.0.dist-info/top_level.txt
TiniLang-1.0.dist-info/RECORD
